{
  "january": "January",
  "2023": "2023",
  "march": "March",
  "2024": "2024",
  "december": "December",
  "2022": "2022",
  "usa": "USA",
  "india": "India",
  "canada": "Canada",
  "france": "France",
  "july": "July",
  "germany": "Germany",
  "june": "June",
  "japan": "Japan",
  "november": "November",
  "uk": "UK",
  "plan a": "Plan A",
  "plan b": "Plan B",
  "plan x": "Plan X",
  "plan y": "Plan Y",
  "plan 1": "Plan 1",
  "plan 2": "Plan 2",
  "north america": "North America",
  "europe": "Europe",
  "asia": "Asia",
  "south america": "South America",
  "australia": "Australia",
  "2024-01-15": "2024-01-15",
  "2024-06-01": "2024-06-01",
  "2023-12-31": "2023-12-31",
  "01": "01",
  "12": "12",
  "03": "03",
  "02": "02",
  "04": "04",
  "05": "05",
  "06": "06",
  "country1": "country1",
  "country2": "country2",
  "summer": "summer",
  "winter": "winter",
  "spring": "spring"
}